odoo/addons/account_invoice_payment_term_date_due/README.rst
odoo/addons/account_invoice_payment_term_date_due/__init__.py
odoo/addons/account_invoice_payment_term_date_due/__manifest__.py
odoo/addons/account_invoice_payment_term_date_due/i18n/account_invoice_payment_term_date_due.pot
odoo/addons/account_invoice_payment_term_date_due/i18n/es.po
odoo/addons/account_invoice_payment_term_date_due/i18n/it.po
odoo/addons/account_invoice_payment_term_date_due/readme/CONTRIBUTORS.md
odoo/addons/account_invoice_payment_term_date_due/readme/DESCRIPTION.md
odoo/addons/account_invoice_payment_term_date_due/static/description/account-invoice-payment-term-due-date.png
odoo/addons/account_invoice_payment_term_date_due/static/description/icon.png
odoo/addons/account_invoice_payment_term_date_due/static/description/index.html
odoo/addons/account_invoice_payment_term_date_due/views/account_move.xml
odoo_addon_account_invoice_payment_term_date_due-18.0.1.0.0.2.dist-info/METADATA
odoo_addon_account_invoice_payment_term_date_due-18.0.1.0.0.2.dist-info/WHEEL
odoo_addon_account_invoice_payment_term_date_due-18.0.1.0.0.2.dist-info/top_level.txt
odoo_addon_account_invoice_payment_term_date_due-18.0.1.0.0.2.dist-info/RECORD
